dpeeg/__init__.py
dpeeg/utils.py
dpeeg/datasets/__init__.py
dpeeg/datasets/base.py
dpeeg/datasets/bnci.py
dpeeg/datasets/download.py
dpeeg/datasets/figshare.py
dpeeg/datasets/gigadb.py
dpeeg/datasets/gin.py
dpeeg/datasets/loaddata.py
dpeeg/datasets/loaddataset.py
dpeeg/datasets/physionet.py
dpeeg/datasets/ukds.py
dpeeg/datasets/utils.py
dpeeg/exps/__init__.py
dpeeg/exps/base.py
dpeeg/exps/holdout.py
dpeeg/exps/kfold.py
dpeeg/exps/loso.py
dpeeg/models/DeepConvNet.py
dpeeg/models/EEGConformer.py
dpeeg/models/EEGNet.py
dpeeg/models/FBCNet.py
dpeeg/models/IFNet.py
dpeeg/models/LightConvNet.py
dpeeg/models/MSVTNet.py
dpeeg/models/ShallowConvNet.py
dpeeg/models/__init__.py
dpeeg/models/utils.py
dpeeg/tools/__init__.py
dpeeg/tools/docs.py
dpeeg/tools/filer.py
dpeeg/tools/logger.py
dpeeg/tools/timer.py
dpeeg/trainer/__init__.py
dpeeg/trainer/base.py
dpeeg/trainer/classifier.py
dpeeg/trainer/stopcriteria.py
dpeeg/trainer/utils.py
dpeeg/transforms/__init__.py
dpeeg/transforms/aug.py
dpeeg/transforms/base.py
dpeeg/transforms/functions.py
dpeeg/transforms/metrics.py
dpeeg/transforms/norm.py
dpeeg/transforms/trans.py
dpeeg-0.4.2.dist-info/LICENSE
dpeeg-0.4.2.dist-info/METADATA
dpeeg-0.4.2.dist-info/WHEEL
dpeeg-0.4.2.dist-info/top_level.txt
dpeeg-0.4.2.dist-info/RECORD
