Metadata-Version: 2.1
Name: dpeeg
Version: 0.4.2
Summary: Deep learning with EEG
Home-page: https://github.com/SheepTAO/dpeeg
Author: SheepTAO
Author-email: sheeptao@outlook.com
License: MIT
Keywords: eeg,deep learning,pytorch
Classifier: Development Status :: 3 - Alpha
Classifier: Intended Audience :: Developers
Classifier: License :: OSI Approved :: MIT License
Classifier: Operating System :: OS Independent
Requires-Python: >=3.10
License-File: LICENSE
Requires-Dist: numpy>=1.21.5
Requires-Dist: einops>=0.7.0
Requires-Dist: seaborn>=0.12.1
Requires-Dist: pooch>=1.6.0
Requires-Dist: mne>=1.6
Requires-Dist: scipy>=1.11.1
Requires-Dist: scikit-learn>=1.0.2
Requires-Dist: tqdm>=4.64.1
Requires-Dist: torchmetrics>=1.0.0
Requires-Dist: torchinfo>=1.5.0
Requires-Dist: tensorboard
Requires-Dist: pandas>=1.5.2
Requires-Dist: openpyxl
